{
  "slug": "find-n-unique-integers-sum-up-to-zero",
  "judge": {
    "type": "any_valid",
    "validator_python": "def validate(args, output):\n    n = args[0]\n    if not isinstance(output, list):\n        return False\n    if len(output) != n:\n        return False\n    for v in output:\n        if not isinstance(v, int) or isinstance(v, bool):\n            return False\n    if len(set(output)) != n:\n        return False\n    return sum(output) == 0\n",
    "validator_javascript": "function validate(args, output) {\n    const n = args[0];\n    if (!Array.isArray(output)) return false;\n    if (output.length !== n) return false;\n    const seen = new Set();\n    let total = 0;\n    for (const v of output) {\n        if (typeof v !== 'number' || !Number.isInteger(v)) return false;\n        seen.add(v);\n        total += v;\n    }\n    if (seen.size !== n) return false;\n    return total === 0;\n}\n"
  },
  "pattern": "Pairing each chosen magnitude with its negation makes the sum cancel automatically, and a lone zero absorbs the leftover element when the count is odd.",
  "hints": [
    "If you put a value and its negative into the answer, that pair contributes nothing to the total.",
    "Build the array from symmetric pairs (x, -x) using distinct magnitudes so every entry is unique.",
    "Emit pairs for as many slots as you can; if one slot is left over because the count is odd, fill it with zero."
  ],
  "constraints": [
    {
      "param": "n",
      "kind": "int",
      "value": [
        1,
        1000
      ]
    }
  ],
  "edge_inputs": [
    {
      "kind": "boundary",
      "description": "smallest count - only zero works",
      "input": [
        1
      ]
    },
    {
      "kind": "edge",
      "description": "odd count needs a zero plus symmetric pairs",
      "input": [
        3
      ]
    },
    {
      "kind": "edge",
      "description": "even count is all symmetric pairs",
      "input": [
        4
      ]
    },
    {
      "kind": "edge",
      "description": "the example odd count",
      "input": [
        5
      ]
    },
    {
      "kind": "boundary",
      "description": "smallest even count",
      "input": [
        2
      ]
    },
    {
      "kind": "trap",
      "description": "larger odd count - duplicates would be easy to introduce by mistake",
      "input": [
        7
      ]
    }
  ],
  "stress": [
    {
      "description": "the maximum count to ensure uniqueness and zero-sum hold at scale",
      "seed": 5,
      "size": 1000,
      "generator_python": "def gen(rng, size):\n    n = rng.randint(1, max(1, min(size, 1000)))\n    return [n]\n",
      "note": "single integer argument; reference must keep all values distinct"
    }
  ],
  "oracle_python": "class Solution:\n    def sumZero(self, n):\n        res = []\n        v = 1\n        while len(res) + 2 <= n:\n            res.append(v)\n            res.append(-v)\n            v += 1\n        if len(res) < n:\n            res.append(0)\n        return res\n",
  "solutions": {
    "python": "class Solution:\n    def sumZero(self, n):\n        res = []\n        for i in range(n // 2):\n            res.append(i + 1)\n            res.append(-(i + 1))\n        if n % 2:\n            res.append(0)\n        return res\n",
    "javascript": "var sumZero = function(n) {\n    const res = [];\n    for (let i = 0; i < Math.floor(n / 2); i++) {\n        res.push(i + 1);\n        res.push(-(i + 1));\n    }\n    if (n % 2) res.push(0);\n    return res;\n};\n"
  },
  "complexity": {
    "time": "O(n)",
    "space": "O(n)"
  },
  "no_anchor_ok": true
}