{
  "slug": "largest-plus-sign",
  "judge": "exact",
  "pattern": "For each cell the largest centred plus is the minimum of its four directional runs of ones, computed by four sweeps of the grid.",
  "hints": [
    "The arm length a plus can have at a cell is limited by how far an unbroken line of ones extends in each of the four directions.",
    "For every cell compute the consecutive ones reaching up, down, left, and right; the plus order centred there is the smallest of those four counts.",
    "Run four directional passes accumulating run lengths (resetting to zero at a mine), keep the per-cell minimum across passes, then return the maximum such minimum over all cells."
  ],
  "constraints": [
    { "param": "n", "kind": "int", "value": [1, 500] },
    { "param": "mines", "kind": "int[][]", "len": [0, 5000], "value": [0, 499] }
  ],
  "edge_inputs": [
    { "kind": "edge", "description": "five by five with one mine yields order two", "input": [5, [[4, 2]]] },
    { "kind": "trap", "description": "single cell mined leaves no plus", "input": [1, [[0, 0]]] },
    { "kind": "boundary", "description": "single cell with no mines is order one", "input": [1, []] },
    { "kind": "edge", "description": "empty grid with no mines gives the full center order", "input": [3, []] },
    { "kind": "trap", "description": "mine at the would-be center forces a smaller plus", "input": [5, [[2, 2]]] },
    { "kind": "edge", "description": "several mines around the border", "input": [4, [[0, 0], [0, 3], [3, 0], [3, 3]]] },
    { "kind": "trap", "description": "two by two fully unmined still only fits order one", "input": [2, []] }
  ],
  "stress": [
    {
      "description": "moderate grids with a random scattering of unique mines",
      "seed": 53,
      "size": 40,
      "generator_python": "def gen(rng, size):\n    n = rng.randint(1, min(40, max(1, size)))\n    cells = [(x, y) for x in range(n) for y in range(n)]\n    rng.shuffle(cells)\n    k = rng.randint(0, min(len(cells), n * n // 2))\n    mines = [[x, y] for (x, y) in cells[:k]]\n    return [n, mines]\n",
      "note": "mines drawn without replacement stay unique and in range"
    }
  ],
  "oracle_python": "class Solution:\n    def orderOfLargestPlusSign(self, n, mines):\n        mineset = set((x, y) for x, y in mines)\n        grid = [[0 if (i, j) in mineset else 1 for j in range(n)] for i in range(n)]\n        best = 0\n        for i in range(n):\n            for j in range(n):\n                if grid[i][j] == 0:\n                    continue\n                k = 1\n                while True:\n                    arm = k\n                    if i - arm < 0 or i + arm >= n or j - arm < 0 or j + arm >= n:\n                        break\n                    if (grid[i - arm][j] and grid[i + arm][j] and grid[i][j - arm] and grid[i][j + arm]):\n                        k += 1\n                    else:\n                        break\n                best = max(best, k)\n        return best\n",
  "solutions": {
    "python": "class Solution:\n    def orderOfLargestPlusSign(self, n, mines):\n        dp = [[n] * n for _ in range(n)]\n        mineset = set((x, y) for x, y in mines)\n        for i in range(n):\n            count = 0\n            for j in range(n):\n                count = 0 if (i, j) in mineset else count + 1\n                dp[i][j] = min(dp[i][j], count)\n            count = 0\n            for j in range(n - 1, -1, -1):\n                count = 0 if (i, j) in mineset else count + 1\n                dp[i][j] = min(dp[i][j], count)\n        best = 0\n        for j in range(n):\n            count = 0\n            for i in range(n):\n                count = 0 if (i, j) in mineset else count + 1\n                dp[i][j] = min(dp[i][j], count)\n            count = 0\n            for i in range(n - 1, -1, -1):\n                count = 0 if (i, j) in mineset else count + 1\n                dp[i][j] = min(dp[i][j], count)\n                best = max(best, dp[i][j])\n        return best\n",
    "javascript": "var orderOfLargestPlusSign = function(n, mines) {\n    const dp = Array.from({length: n}, () => new Array(n).fill(n));\n    const mineset = new Set(mines.map(([x, y]) => x * n + y));\n    const mined = (i, j) => mineset.has(i * n + j);\n    for (let i = 0; i < n; i++) {\n        let count = 0;\n        for (let j = 0; j < n; j++) {\n            count = mined(i, j) ? 0 : count + 1;\n            dp[i][j] = Math.min(dp[i][j], count);\n        }\n        count = 0;\n        for (let j = n - 1; j >= 0; j--) {\n            count = mined(i, j) ? 0 : count + 1;\n            dp[i][j] = Math.min(dp[i][j], count);\n        }\n    }\n    let best = 0;\n    for (let j = 0; j < n; j++) {\n        let count = 0;\n        for (let i = 0; i < n; i++) {\n            count = mined(i, j) ? 0 : count + 1;\n            dp[i][j] = Math.min(dp[i][j], count);\n        }\n        count = 0;\n        for (let i = n - 1; i >= 0; i--) {\n            count = mined(i, j) ? 0 : count + 1;\n            dp[i][j] = Math.min(dp[i][j], count);\n            best = Math.max(best, dp[i][j]);\n        }\n    }\n    return best;\n};\n"
  },
  "complexity": { "time": "O(n^2)", "space": "O(n^2)" }
}
