{
  "slug": "palindrome-partitioning-ii",
  "judge": "exact",
  "pattern": "A one-dimensional cut array, filled with help from a precomputed palindrome table, gives the fewest cuts by extending the best prefix solution at each position.",
  "hints": [
    "The answer is one less than the smallest number of palindromic pieces the string can be split into.",
    "Precompute which substrings are palindromes, then let cuts[i] be the minimum cuts for the prefix of length i+1, updating it from every j where the tail s[j..i] is a palindrome.",
    "Build a boolean table pal[j][i] for s[j..i] being a palindrome; set cuts[i] = 0 if pal[0][i], else min over j<=i of cuts[j-1]+1 when pal[j][i]; return cuts[n-1]."
  ],
  "constraints": [
    { "param": "s", "kind": "str", "len": [1, 2000] }
  ],
  "edge_inputs": [
    { "kind": "edge", "description": "one cut splits into two palindromes", "input": ["aab"] },
    { "kind": "boundary", "description": "single character needs no cut", "input": ["a"] },
    { "kind": "trap", "description": "two distinct characters need one cut", "input": ["ab"] },
    { "kind": "edge", "description": "whole string already a palindrome, zero cuts", "input": ["racecar"] },
    { "kind": "trap", "description": "all distinct characters force a cut between each", "input": ["abcde"] },
    { "kind": "edge", "description": "nested palindromes allow few cuts", "input": ["aabbaab"] },
    { "kind": "trap", "description": "greedy longest-first would over-cut here", "input": ["cdddcd"] },
    { "kind": "edge", "description": "all same character, zero cuts", "input": ["aaaaaa"] }
  ],
  "stress": [
    {
      "description": "random small-alphabet strings so palindromic substrings appear often",
      "seed": 37,
      "size": 300,
      "generator_python": "def gen(rng, size):\n    n = max(1, min(size, 600))\n    return [''.join(rng.choice('abc') for _ in range(n))]\n",
      "note": "three-letter alphabet yields frequent palindromic runs"
    }
  ],
  "oracle_python": "class Solution:\n    def minCut(self, s):\n        n = len(s)\n        import functools\n        def is_pal(a, b):\n            while a < b:\n                if s[a] != s[b]:\n                    return False\n                a += 1\n                b -= 1\n            return True\n        INF = float('inf')\n        dp = [INF] * (n + 1)\n        dp[0] = -1\n        for i in range(1, n + 1):\n            for j in range(i):\n                if is_pal(j, i - 1):\n                    if dp[j] + 1 < dp[i]:\n                        dp[i] = dp[j] + 1\n        return dp[n]\n",
  "solutions": {
    "python": "class Solution:\n    def minCut(self, s):\n        n = len(s)\n        pal = [[False] * n for _ in range(n)]\n        for i in range(n):\n            pal[i][i] = True\n        for length in range(2, n + 1):\n            for j in range(0, n - length + 1):\n                i = j + length - 1\n                if s[j] == s[i] and (length == 2 or pal[j+1][i-1]):\n                    pal[j][i] = True\n        cuts = [0] * n\n        for i in range(n):\n            if pal[0][i]:\n                cuts[i] = 0\n            else:\n                best = i\n                for j in range(1, i + 1):\n                    if pal[j][i] and cuts[j-1] + 1 < best:\n                        best = cuts[j-1] + 1\n                cuts[i] = best\n        return cuts[n-1]\n",
    "javascript": "var minCut = function(s) {\n    const n = s.length;\n    const pal = Array.from({length: n}, () => new Array(n).fill(false));\n    for (let i = 0; i < n; i++) pal[i][i] = true;\n    for (let length = 2; length <= n; length++) {\n        for (let j = 0; j + length - 1 < n; j++) {\n            const i = j + length - 1;\n            if (s[j] === s[i] && (length === 2 || pal[j+1][i-1])) pal[j][i] = true;\n        }\n    }\n    const cuts = new Array(n).fill(0);\n    for (let i = 0; i < n; i++) {\n        if (pal[0][i]) { cuts[i] = 0; continue; }\n        let best = i;\n        for (let j = 1; j <= i; j++) {\n            if (pal[j][i] && cuts[j-1] + 1 < best) best = cuts[j-1] + 1;\n        }\n        cuts[i] = best;\n    }\n    return cuts[n-1];\n};\n"
  },
  "complexity": { "time": "O(n^2)", "space": "O(n^2)" }
}
