{
  "slug": "remove-one-element-to-make-the-array-strictly-increasing",
  "judge": "exact",
  "pattern": "At the first descent you have exactly two repair choices, and a single greedy decision tells you whether one removal suffices.",
  "hints": [
    "A strictly increasing array has at most zero violations of nums[i-1] < nums[i].",
    "If you find more than one violation you cannot fix it with a single removal.",
    "At the first violation, try removing either the earlier or the later element and check whether the rest stays strictly increasing."
  ],
  "constraints": [
    { "param": "nums", "kind": "int[]", "len": [2, 1000], "value": [1, 1000] }
  ],
  "edge_inputs": [
    { "kind": "edge", "description": "remove a spike in the middle", "input": [[1, 2, 10, 5, 7]] },
    { "kind": "trap", "description": "two violations cannot be fixed", "input": [[2, 3, 1, 2]] },
    { "kind": "trap", "description": "all equal needs more than one removal", "input": [[1, 1, 1]] },
    { "kind": "boundary", "description": "two distinct already increasing", "input": [[1, 2]] },
    { "kind": "edge", "description": "violation at the very start", "input": [[100, 1, 2, 3]] },
    { "kind": "edge", "description": "violation at the very end", "input": [[1, 2, 3, 2]] },
    { "kind": "trap", "description": "removing earlier element fails but later succeeds", "input": [[1, 5, 3, 4]] },
    { "kind": "trap", "description": "removing later element fails but earlier succeeds", "input": [[2, 3, 1, 4]] }
  ],
  "stress": [
    {
      "description": "near-increasing arrays with occasional dips",
      "seed": 33,
      "size": 1000,
      "generator_python": "def gen(rng, size):\n    n = max(2, size)\n    cur = 1\n    a = []\n    for _ in range(n):\n        cur += rng.randrange(0, 3)\n        a.append(cur)\n    if rng.random() < 0.7:\n        idx = rng.randrange(0, n)\n        a[idx] = rng.randrange(1, 1001)\n    return [a]\n"
    }
  ],
  "oracle_python": "class Solution:\n    def canBeIncreasing(self, nums):\n        def inc(arr):\n            return all(arr[i - 1] < arr[i] for i in range(1, len(arr)))\n        if inc(nums):\n            return True\n        for i in range(len(nums)):\n            if inc(nums[:i] + nums[i + 1:]):\n                return True\n        return False\n",
  "solutions": {
    "python": "class Solution:\n    def canBeIncreasing(self, nums):\n        removed = False\n        prev = nums[0]\n        for i in range(1, len(nums)):\n            if nums[i] <= prev:\n                if removed:\n                    return False\n                removed = True\n                if i == 1 or nums[i] > nums[i - 2]:\n                    prev = nums[i]\n                else:\n                    pass\n            else:\n                prev = nums[i]\n        return True\n",
    "javascript": "var canBeIncreasing = function(nums) {\n    let removed = false;\n    let prev = nums[0];\n    for (let i = 1; i < nums.length; i++) {\n        if (nums[i] <= prev) {\n            if (removed) return false;\n            removed = true;\n            if (i === 1 || nums[i] > nums[i - 2]) {\n                prev = nums[i];\n            }\n        } else {\n            prev = nums[i];\n        }\n    }\n    return true;\n};\n"
  },
  "complexity": { "time": "O(n)", "space": "O(1)" }
}
