{
  "slug": "rotated-digits",
  "judge": "exact",
  "pattern": "A number survives a 180-degree rotation only if every digit is rotatable, and it becomes a different number only if at least one digit actually changes, so counting reduces to a per-digit classification over each value in the range.",
  "hints": [
    "Sort the digits into three buckets: ones that stay the same, ones that turn into a different valid digit, and ones that become garbage.",
    "A number counts only if it contains no garbage digit and at least one digit that flips to something different.",
    "For each value check its digits: reject immediately on a 3, 4, or 7, and mark it good if it also contains at least one 2, 5, 6, or 9; tally the goods."
  ],
  "constraints": [
    { "param": "n", "kind": "int", "value": [1, 10000] }
  ],
  "edge_inputs": [
    { "kind": "edge", "description": "first example, four good numbers up to ten", "input": [10] },
    { "kind": "boundary", "description": "one has no flipping digit so zero good", "input": [1] },
    { "kind": "boundary", "description": "two is the first good number", "input": [2] },
    { "kind": "trap", "description": "numbers made only of self-rotating digits do not count", "input": [11] },
    { "kind": "trap", "description": "just below a value containing an invalid digit", "input": [29] },
    { "kind": "edge", "description": "upper end of the range", "input": [10000] },
    { "kind": "edge", "description": "round hundred boundary", "input": [100] }
  ],
  "stress": [
    {
      "description": "random upper bounds across the full allowed range",
      "seed": 53,
      "size": 9000,
      "generator_python": "def gen(rng, size):\n    n = rng.randint(1, min(10000, max(1, size)))\n    return [n]\n",
      "note": "the reference counts directly so any n within range is fast"
    }
  ],
  "oracle_python": "class Solution:\n    def rotatedDigits(self, n):\n        invalid = set('347')\n        flips = set('2569')\n        count = 0\n        for x in range(1, n + 1):\n            digs = str(x)\n            if any(d in invalid for d in digs):\n                continue\n            if any(d in flips for d in digs):\n                count += 1\n        return count\n",
  "solutions": {
    "python": "class Solution:\n    def rotatedDigits(self, n):\n        good = 0\n        for x in range(1, n + 1):\n            has_flip = False\n            valid = True\n            y = x\n            while y > 0:\n                d = y % 10\n                if d in (3, 4, 7):\n                    valid = False\n                    break\n                if d in (2, 5, 6, 9):\n                    has_flip = True\n                y //= 10\n            if valid and has_flip:\n                good += 1\n        return good\n",
    "javascript": "var rotatedDigits = function(n) {\n    let good = 0;\n    for (let x = 1; x <= n; x++) {\n        let hasFlip = false;\n        let valid = true;\n        let y = x;\n        while (y > 0) {\n            const d = y % 10;\n            if (d === 3 || d === 4 || d === 7) { valid = false; break; }\n            if (d === 2 || d === 5 || d === 6 || d === 9) hasFlip = true;\n            y = Math.floor(y / 10);\n        }\n        if (valid && hasFlip) good++;\n    }\n    return good;\n};\n"
  },
  "complexity": { "time": "O(n log n)", "space": "O(1)" }
}
