{
  "slug": "smallest-number-with-all-set-bits",
  "judge": "exact",
  "pattern": "Numbers made entirely of set bits are exactly the 'one less than a power of two' family, so the answer is just the first member of that short, easily-enumerated family that reaches n.",
  "hints": [
    "A number whose binary form is all 1s is always exactly one less than some power of two.",
    "Starting from the smallest such number, repeatedly double it and add one until it is no longer smaller than n.",
    "There's no need to search bit by bit -- the sequence 1, 3, 7, 15, 31, ... grows fast enough that you'll reach or pass n within about as many steps as n has bits."
  ],
  "constraints": [
    {
      "param": "n",
      "kind": "int",
      "value": [
        1,
        1000
      ]
    }
  ],
  "edge_inputs": [
    {
      "kind": "edge",
      "description": "statement example one",
      "input": [
        5
      ]
    },
    {
      "kind": "edge",
      "description": "statement example two",
      "input": [
        10
      ]
    },
    {
      "kind": "edge",
      "description": "statement example three, n already all-ones",
      "input": [
        3
      ]
    },
    {
      "kind": "boundary",
      "description": "smallest possible n",
      "input": [
        1
      ]
    },
    {
      "kind": "boundary",
      "description": "largest possible n",
      "input": [
        1000
      ]
    },
    {
      "kind": "trap",
      "description": "n one more than an all-ones number",
      "input": [
        8
      ]
    },
    {
      "kind": "trap",
      "description": "n exactly a power of two",
      "input": [
        16
      ]
    }
  ],
  "stress": [
    {
      "description": "every n from 1 to 1000",
      "seed": 12,
      "size": 1000,
      "generator_python": "def gen(rng, size):\n    return [rng.randint(1, 1000)]\n"
    }
  ],
  "oracle_python": "class Solution:\n    def smallestNumber(self, n):\n        bits = n.bit_length()\n        x = (1 << bits) - 1\n        if x < n:\n            x = (1 << (bits + 1)) - 1\n        return x\n",
  "solutions": {
    "python": "class Solution:\n    def smallestNumber(self, n):\n        x = 1\n        while x < n:\n            x = x * 2 + 1\n        return x\n",
    "javascript": "var smallestNumber = function(n) {\n    let x = 1;\n    while (x < n) {\n        x = x * 2 + 1;\n    }\n    return x;\n};\n"
  },
  "complexity": {
    "time": "O(log n)",
    "space": "O(1)"
  }
}