{
  "slug": "sort-colors",
  "judge": { "type": "in_place", "arg_index": 0 },
  "pattern": "The Dutch-national-flag partition sweeps once with three pointers, swapping values to the correct end so the three categories sort in place without counting.",
  "hints": [
    "There are only three possible values, so the sorted result is just all of the lowest, then the middles, then the highest.",
    "Keep a boundary for the placed lows on the left and the placed highs on the right while a scanner moves through the middle.",
    "When the scanner sees a low, swap it to the low boundary and advance both; on a high, swap it to the high boundary and shrink that boundary without advancing; on a middle, just advance the scanner."
  ],
  "constraints": [
    { "param": "nums", "kind": "int[]", "len": [1, 300], "value": [0, 2] }
  ],
  "edge_inputs": [
    { "kind": "edge", "description": "mixed three colors", "input": [[2, 0, 2, 1, 1, 0]] },
    { "kind": "edge", "description": "three distinct values", "input": [[2, 0, 1]] },
    { "kind": "boundary", "description": "single element", "input": [[1]] },
    { "kind": "trap", "description": "already sorted stays sorted", "input": [[0, 0, 1, 1, 2, 2]] },
    { "kind": "trap", "description": "reverse sorted", "input": [[2, 2, 1, 1, 0, 0]] },
    { "kind": "trap", "description": "all the same value", "input": [[1, 1, 1, 1]] },
    { "kind": "edge", "description": "only two of the three colors present", "input": [[2, 0, 0, 2]] },
    { "kind": "boundary", "description": "two elements out of order", "input": [[2, 0]] }
  ],
  "stress": [
    {
      "description": "random arrays of zeros, ones, and twos",
      "seed": 75,
      "size": 300,
      "generator_python": "def gen(rng, size):\n    n = max(1, size)\n    return [[rng.randint(0, 2) for _ in range(n)]]\n",
      "note": "uniform distribution exercises all three partitions"
    }
  ],
  "oracle_python": "class Solution:\n    def sortColors(self, nums):\n        nums.sort()\n",
  "solutions": {
    "python": "class Solution:\n    def sortColors(self, nums):\n        low, mid, high = 0, 0, len(nums) - 1\n        while mid <= high:\n            if nums[mid] == 0:\n                nums[low], nums[mid] = nums[mid], nums[low]\n                low += 1\n                mid += 1\n            elif nums[mid] == 1:\n                mid += 1\n            else:\n                nums[mid], nums[high] = nums[high], nums[mid]\n                high -= 1\n",
    "javascript": "var sortColors = function(nums) {\n    let low = 0, mid = 0, high = nums.length - 1;\n    while (mid <= high) {\n        if (nums[mid] === 0) {\n            [nums[low], nums[mid]] = [nums[mid], nums[low]];\n            low++;\n            mid++;\n        } else if (nums[mid] === 1) {\n            mid++;\n        } else {\n            [nums[mid], nums[high]] = [nums[high], nums[mid]];\n            high--;\n        }\n    }\n};\n"
  },
  "complexity": { "time": "O(n)", "space": "O(1)" }
}
