{
  "slug": "spiral-matrix-iii",
  "judge": "exact",
  "no_anchor_ok": true,
  "pattern": "Walk clockwise in a repeating East-South-West-North pattern where each direction pair shares an increasing step length, recording only cells that fall inside the grid boundary.",
  "hints": [
    "The spiral alternates through four directions; each pair of consecutive turns shares the same run length before that length grows by one.",
    "You can walk the full spiral path — even through out-of-bounds positions — but only append a coordinate to the result when it lies inside the grid.",
    "Repeat direction changes in the cycle E→S→W→N, increment the step length after every two turns, and stop once you have collected all rows×cols grid cells."
  ],
  "constraints": [
    { "param": "rows", "kind": "int", "value": [1, 100] },
    { "param": "cols", "kind": "int", "value": [1, 100] },
    { "param": "rStart", "kind": "int", "value": [0, 99] },
    { "param": "cStart", "kind": "int", "value": [0, 99] }
  ],
  "edge_inputs": [
    { "kind": "edge", "description": "single-row grid starting at the left edge, spiral is just a rightward sweep", "input": [1, 4, 0, 0] },
    { "kind": "edge", "description": "5x6 grid starting near the middle, exercises many out-of-bounds passes", "input": [5, 6, 1, 4] },
    { "kind": "boundary", "description": "1x1 grid, only one cell to visit", "input": [1, 1, 0, 0] },
    { "kind": "boundary", "description": "single column grid, spiral collapses to vertical traversal", "input": [4, 1, 0, 0] },
    { "kind": "trap", "description": "start at bottom-right corner, spiral exits and re-enters many times", "input": [3, 3, 2, 2] },
    { "kind": "trap", "description": "start at top-left corner of a wide grid", "input": [2, 5, 0, 0] },
    { "kind": "edge", "description": "square grid starting at center", "input": [4, 4, 1, 1] },
    { "kind": "boundary", "description": "1x100 row, start at right end, spiral is leftward", "input": [1, 100, 0, 99] },
    { "kind": "boundary", "description": "100x1 column, start at bottom", "input": [100, 1, 99, 0] }
  ],
  "stress": [
    {
      "description": "random grid dimensions and random valid starting positions",
      "seed": 42,
      "size": 80,
      "generator_python": "def gen(rng, size):\n    rows = rng.randint(1, min(100, size))\n    cols = rng.randint(1, min(100, size))\n    rStart = rng.randint(0, rows - 1)\n    cStart = rng.randint(0, cols - 1)\n    return [rows, cols, rStart, cStart]\n",
      "note": "covers varied grid shapes and starting positions including off-center and corner starts"
    }
  ],
  "oracle_python": "class Solution:\n    def spiralMatrixIII(self, rows: int, cols: int, rStart: int, cStart: int):\n        result = []\n        r, c = rStart, cStart\n        # Brute-force: simulate step by step in E,S,W,N order\n        dirs = [(0, 1), (1, 0), (0, -1), (-1, 0)]\n        di = 0\n        step = 1\n        total = rows * cols\n        while len(result) < total:\n            for _ in range(2):\n                dr, dc = dirs[di % 4]\n                for _ in range(step):\n                    if 0 <= r < rows and 0 <= c < cols:\n                        result.append([r, c])\n                    if len(result) == total:\n                        return result\n                    r += dr\n                    c += dc\n                di += 1\n            step += 1\n        return result\n",
  "solutions": {
    "python": "class Solution:\n    def spiralMatrixIII(self, rows: int, cols: int, rStart: int, cStart: int):\n        result = []\n        r, c = rStart, cStart\n        dirs = [(0, 1), (1, 0), (0, -1), (-1, 0)]\n        di = 0\n        step = 1\n        total = rows * cols\n        while len(result) < total:\n            for _ in range(2):\n                dr, dc = dirs[di % 4]\n                for _ in range(step):\n                    if 0 <= r < rows and 0 <= c < cols:\n                        result.append([r, c])\n                    r += dr\n                    c += dc\n                di += 1\n            step += 1\n        return result\n",
    "javascript": "var spiralMatrixIII = function(rows, cols, rStart, cStart) {\n    const result = [];\n    const dirs = [[0, 1], [1, 0], [0, -1], [-1, 0]];\n    let r = rStart, c = cStart;\n    let di = 0, step = 1;\n    const total = rows * cols;\n    while (result.length < total) {\n        for (let t = 0; t < 2; t++) {\n            const [dr, dc] = dirs[di % 4];\n            for (let i = 0; i < step; i++) {\n                if (r >= 0 && r < rows && c >= 0 && c < cols) {\n                    result.push([r, c]);\n                }\n                r += dr;\n                c += dc;\n            }\n            di++;\n        }\n        step++;\n    }\n    return result;\n};\n"
  },
  "complexity": { "time": "O((max(rows,cols))^2)", "space": "O(rows*cols)" }
}
