{
  "slug": "swapping-nodes-in-a-linked-list",
  "judge": "exact",
  "io_types": { "params": ["linked_list", "json"], "returns": "linked_list" },
  "pattern": "Two pointers separated by exactly k-1 steps let you find the k-th node from the front and, once the leader reaches the end, the k-th node from the back simultaneously, so a single pass finds both swap targets.",
  "hints": [
    "You need the k-th node counting from the front and the k-th node counting from the back -- finding the second one without knowing the length up front is the real trick.",
    "Walk a pointer k-1 steps ahead to mark the front node, then start a second pointer at the head and advance both together until the first pointer hits the last node -- the second pointer is now exactly k-th from the end.",
    "Once you have references to both nodes, just swap their val fields (not the nodes themselves) and return the original head; if the two references are the same node, swapping its value with itself is a harmless no-op."
  ],
  "constraints": [
    { "param": "head", "kind": "linked_list", "len": [1, 100000], "value": [0, 100] },
    { "param": "k", "kind": "int", "value": [1, 100000] }
  ],
  "edge_inputs": [
    { "kind": "edge", "description": "statement example, odd length, k picks distinct front/back nodes", "input": [[1, 2, 3, 4, 5], 2] },
    { "kind": "edge", "description": "statement example, longer list", "input": [[7, 9, 6, 6, 7, 8, 3, 0, 9, 5], 5] },
    { "kind": "boundary", "description": "single node, k=1 swaps a node with itself", "input": [[42], 1] },
    { "kind": "trap", "description": "k picks the exact middle of an odd-length list, front and back node are the same", "input": [[1, 2, 3, 4, 5], 3] },
    { "kind": "trap", "description": "k=1, swap head with tail", "input": [[10, 20, 30, 40], 1] },
    { "kind": "trap", "description": "k equals the list length, swap tail with head", "input": [[10, 20, 30, 40], 4] },
    { "kind": "edge", "description": "two-node list, k=1 swaps the only pair", "input": [[1, 2], 1] },
    { "kind": "boundary", "description": "long uniform list to keep the two-pointer walk honest", "input": [[5, 5, 5, 5, 5, 5, 5, 5], 3] }
  ],
  "stress": [
    {
      "description": "random-length lists with random values and a k drawn from the valid range for that length",
      "seed": 7,
      "size": 5000,
      "generator_python": "def gen(rng, size):\n    n = max(1, min(size, 100000))\n    vals = [rng.randint(0, 100) for _ in range(n)]\n    k = rng.randint(1, n)\n    return [vals, k]\n",
      "note": "k always within [1, n] as required by the constraints"
    }
  ],
  "oracle_python": "class Solution:\n    def swapNodes(self, head, k):\n        vals = []\n        node = head\n        while node:\n            vals.append(node.val)\n            node = node.next\n        n = len(vals)\n        vals[k - 1], vals[n - k] = vals[n - k], vals[k - 1]\n        dummy = ListNode(0)\n        tail = dummy\n        for v in vals:\n            tail.next = ListNode(v)\n            tail = tail.next\n        return dummy.next\n",
  "solutions": {
    "python": "class Solution:\n    def swapNodes(self, head, k):\n        first = head\n        for _ in range(k - 1):\n            first = first.next\n        second = head\n        runner = first\n        while runner.next:\n            runner = runner.next\n            second = second.next\n        first.val, second.val = second.val, first.val\n        return head\n",
    "javascript": "var swapNodes = function(head, k) {\n    let first = head;\n    for (let i = 0; i < k - 1; i++) {\n        first = first.next;\n    }\n    let second = head;\n    let runner = first;\n    while (runner.next) {\n        runner = runner.next;\n        second = second.next;\n    }\n    const tmp = first.val;\n    first.val = second.val;\n    second.val = tmp;\n    return head;\n};\n"
  },
  "complexity": { "time": "O(n)", "space": "O(1)" }
}
